russian_sme_registry/__init__.py
russian_sme_registry/__main__.py
russian_sme_registry/assets/__init__.py
russian_sme_registry/assets/abbr.csv
russian_sme_registry/assets/activity_codes_classifier.csv
russian_sme_registry/assets/assets_manager.py
russian_sme_registry/assets/cities.csv
russian_sme_registry/assets/cities_additional.csv
russian_sme_registry/assets/regions.csv
russian_sme_registry/assets/rosstat-org-stats.csv
russian_sme_registry/assets/settlements.csv
russian_sme_registry/main.py
russian_sme_registry/stages/__init__.py
russian_sme_registry/stages/aggregate.py
russian_sme_registry/stages/download.py
russian_sme_registry/stages/extract.py
russian_sme_registry/stages/geocode.py
russian_sme_registry/stages/panelize.py
russian_sme_registry/stages/spark_stage.py
russian_sme_registry/tests/__init__.py
russian_sme_registry/tests/common.py
russian_sme_registry/tests/conftest.py
russian_sme_registry/tests/data/empl/data-test-empl-1.zip
russian_sme_registry/tests/data/empl/data-test-empl-2.zip
russian_sme_registry/tests/data/empl/data-test-empl-extracted-1.csv
russian_sme_registry/tests/data/empl/data-test-empl-extracted-2.csv
russian_sme_registry/tests/data/empl/data-test-empl-extracted-3.csv
russian_sme_registry/tests/data/empl/empl.html
russian_sme_registry/tests/data/empl/test-aggregated.csv
russian_sme_registry/tests/data/revexp/data-test-revexp-1.zip
russian_sme_registry/tests/data/revexp/data-test-revexp-2.zip
russian_sme_registry/tests/data/revexp/data-test-revexp-extracted-1.csv
russian_sme_registry/tests/data/revexp/data-test-revexp-extracted-2.csv
russian_sme_registry/tests/data/revexp/data-test-revexp-extracted-3.csv
russian_sme_registry/tests/data/revexp/revexp.html
russian_sme_registry/tests/data/revexp/test-aggregated.csv
russian_sme_registry/tests/data/sme/data-sme-test-extracted-1.csv
russian_sme_registry/tests/data/sme/data-sme-test-extracted-2.csv
russian_sme_registry/tests/data/sme/data-sme-test-extracted-3.csv
russian_sme_registry-1.0.0b6.dist-info/LICENSE
russian_sme_registry-1.0.0b6.dist-info/METADATA
russian_sme_registry-1.0.0b6.dist-info/WHEEL
russian_sme_registry-1.0.0b6.dist-info/entry_points.txt
russian_sme_registry-1.0.0b6.dist-info/RECORD
