Metadata-Version: 2.1
Name: russian-sme-registry
Version: 1.0.0b6
Summary: A command-line tool to get a georeferenced dataset of Russian small and medium-sized enterprises (SME) from open data of Federal Tax Service
License: GPL-3.0-or-later
Author: Pavel Syomin
Author-email: pas.ntg@gmail.com
Requires-Python: >=3.10,<4.0
Classifier: Development Status :: 4 - Beta
Classifier: Environment :: Console
Classifier: Intended Audience :: Developers
Classifier: Intended Audience :: Science/Research
Classifier: License :: OSI Approved :: GNU General Public License v3 or later (GPLv3+)
Classifier: Programming Language :: Python :: 3
Classifier: Programming Language :: Python :: 3.10
Classifier: Programming Language :: Python :: 3.11
Classifier: Programming Language :: Python :: 3.12
Classifier: Programming Language :: Python :: 3.13
Classifier: Topic :: Scientific/Engineering
Classifier: Topic :: Utilities
Requires-Dist: beautifulsoup4 (>=4.12.3,<5.0.0)
Requires-Dist: fuzzywuzzy (>=0.18.0,<0.19.0)
Requires-Dist: lxml (>=5.1.0,<6.0.0)
Requires-Dist: numpy (>=1.26.3,<2.0.0)
Requires-Dist: openpyxl (>=3.1.5,<4.0.0)
Requires-Dist: pandas (>=2.2.0,<3.0.0)
Requires-Dist: pyarrow (>=20.0.0,<21.0.0)
Requires-Dist: pyspark (>=3.4.1,<4.0.0)
Requires-Dist: python-levenshtein (>=0.23.0,<0.24.0)
Requires-Dist: requests (>=2.31.0,<3.0.0)
Requires-Dist: tqdm (>=4.66.1,<5.0.0)
Requires-Dist: typer[all] (>=0.9.0,<0.10.0)
